[
  { "name": "New Year's Day", "date": "2026-01-01", "localName": "Año Nuevo" },
  { "name": "Holy Thursday", "date": "2026-04-02", "localName": "Jueves Santo" },
  { "name": "Good Friday", "date": "2026-04-03", "localName": "Viernes Santo" },
  { "name": "Labour Day", "date": "2026-05-01", "localName": "Día del Trabajo" },
  { "name": "Independence Day", "date": "2026-09-15", "localName": "Día de la Independencia" },
  { "name": "All Saints' Day", "date": "2026-11-01", "localName": "Día de Todos los Santos" },
  { "name": "Christmas Day", "date": "2026-12-25", "localName": "Navidad" }
]
